accept_language/__init__.py
accept_language/accept_language.py
parse_accept_language-0.1.1.dist-info/DESCRIPTION.rst
parse_accept_language-0.1.1.dist-info/METADATA
parse_accept_language-0.1.1.dist-info/RECORD
parse_accept_language-0.1.1.dist-info/WHEEL
parse_accept_language-0.1.1.dist-info/metadata.json
parse_accept_language-0.1.1.dist-info/top_level.txt
